pyturtle/__init__.py
pyturtle/pyturtle.py
pyturtle/shapes/__init__.py
pyturtle/shapes/arc.py
pyturtle/shapes/circle.py
pyturtle/shapes/circle_class.py
pyturtle/shapes/line.py
pyturtle/shapes/point.py
pyturtle/shapes/polygon_class.py
pyturtle/shapes/random_walk_class.py
pyturtle/shapes/shape.py
pyturtle/shapes/triangle.py
pyturtle-0.1.9.dist-info/LICENSE
pyturtle-0.1.9.dist-info/METADATA
pyturtle-0.1.9.dist-info/WHEEL
pyturtle-0.1.9.dist-info/RECORD
