Metadata-Version: 2.1
Name: pyturtle
Version: 0.1.9
Summary: A package to generate coordinates of shapes to easily draw using the Turtle package!
License: MIT
Author: Travis DePriest
Requires-Python: >=3.9,<3.11
Classifier: License :: OSI Approved :: MIT License
Classifier: Programming Language :: Python :: 3
Classifier: Programming Language :: Python :: 3.9
Classifier: Programming Language :: Python :: 3.10
Requires-Dist: numpy (>=1.26.0,<2.0.0)
